core/__init__.py
core/help.py
aiogitignore-1.1.dist-info/LICENSE
aiogitignore-1.1.dist-info/METADATA
aiogitignore-1.1.dist-info/WHEEL
aiogitignore-1.1.dist-info/top_level.txt
aiogitignore-1.1.dist-info/RECORD
