Metadata-Version: 2.1
Name: aiogitignore
Version: 1.1
Summary: A simple command line tool to generate .gitignore files
Author: Aiglon Doré
Author-email: aiglondore@outlook.com
License-File: LICENSE
Requires-Dist: aiohttp
Requires-Dist: async-lru
